inpython/__init__.py
inpython/__main__.py
inpython/aotools/__init__.py
inpython/aotools/aogeo.py
inpython/ingraph/__init__.py
inpython/ingraph/ingraph.py
inpython/inqrcode/__init__.py
inpython/inqrcode/inqrcode.py
inpython/inqrcode/paymentqrcode.py
inpython/inrest/__init__.py
inpython/inrest/in_jwt.py
inpython/intools/Servalux-devis.py
inpython/intools/__init__.py
inpython/intools/in_docx.py
inpython/intools/in_projet.py
inpython/intools/in_test.py
inpython/intools/xls_to_csv.py
inpython/inxml/__init__.py
inpython/inxml/validator.py
inpython_package-1.1.7.dist-info/licenses/LICENSE.txt
inpython_package-1.1.7.dist-info/METADATA
inpython_package-1.1.7.dist-info/WHEEL
inpython_package-1.1.7.dist-info/top_level.txt
inpython_package-1.1.7.dist-info/RECORD
