Metadata-Version: 2.4
Name: inpython-package
Version: 1.1.7
Summary: # Infodata's IN-Tools U2Python Package
Home-page: https://bitbucket.org/infodata-dev/inpython
Author: infodata
Author-email: efv@infodata.lu
License: MIT
Requires-Python: >=3.4
License-File: LICENSE.txt
Requires-Dist: msal>=1.22
Requires-Dist: qrcode
Requires-Dist: requests
Requires-Dist: qrcode[pil]
Requires-Dist: dotenv
Dynamic: author
Dynamic: author-email
Dynamic: description
Dynamic: description-content-type
Dynamic: home-page
Dynamic: license
Dynamic: license-file
Dynamic: requires-dist
Dynamic: requires-python
Dynamic: summary
